skynet_ml/__init__.py
skynet_ml/clustering/__init__.py
skynet_ml/clustering/centroids.py
skynet_ml/clustering/dbscan.py
skynet_ml/clustering/distances.py
skynet_ml/clustering/kmeans.py
skynet_ml/metrics/__init__.py
skynet_ml/metrics/base.py
skynet_ml/metrics/classification/__init__.py
skynet_ml/metrics/classification/accuracy.py
skynet_ml/metrics/classification/confusion_matrix.py
skynet_ml/metrics/classification/fscore.py
skynet_ml/metrics/classification/precision.py
skynet_ml/metrics/classification/recall.py
skynet_ml/metrics/regression/__init__.py
skynet_ml/metrics/regression/mae.py
skynet_ml/metrics/regression/mse.py
skynet_ml/metrics/regression/rmse.py
skynet_ml/metrics/regression/rsquared.py
skynet_ml/nn/__init__.py
skynet_ml/nn/activations/__init__.py
skynet_ml/nn/activations/base.py
skynet_ml/nn/activations/leaky_relu.py
skynet_ml/nn/activations/linear.py
skynet_ml/nn/activations/relu.py
skynet_ml/nn/activations/sigmoid.py
skynet_ml/nn/activations/softmax.py
skynet_ml/nn/activations/tanh.py
skynet_ml/nn/initializers/__init__.py
skynet_ml/nn/initializers/base.py
skynet_ml/nn/initializers/constant.py
skynet_ml/nn/initializers/he.py
skynet_ml/nn/initializers/normal.py
skynet_ml/nn/initializers/uniform.py
skynet_ml/nn/initializers/xavier.py
skynet_ml/nn/layers/__init__.py
skynet_ml/nn/layers/base.py
skynet_ml/nn/layers/dense.py
skynet_ml/nn/losses/__init__.py
skynet_ml/nn/losses/base.py
skynet_ml/nn/losses/bce.py
skynet_ml/nn/losses/cce.py
skynet_ml/nn/losses/mse.py
skynet_ml/nn/models/__init__.py
skynet_ml/nn/models/sequential.py
skynet_ml/nn/optimizers/__init__.py
skynet_ml/nn/optimizers/adagrad.py
skynet_ml/nn/optimizers/adam.py
skynet_ml/nn/optimizers/base.py
skynet_ml/nn/optimizers/rmsprop.py
skynet_ml/nn/optimizers/sgd.py
skynet_ml/nn/regularizers/__init__.py
skynet_ml/nn/regularizers/base.py
skynet_ml/nn/regularizers/l1.py
skynet_ml/nn/regularizers/l1l2.py
skynet_ml/nn/regularizers/l2.py
skynet_ml/utils/__init__.py
skynet_ml/utils/factories/__init__.py
skynet_ml-1.2.0.7.dist-info/LICENSE
skynet_ml-1.2.0.7.dist-info/METADATA
skynet_ml-1.2.0.7.dist-info/WHEEL
skynet_ml-1.2.0.7.dist-info/top_level.txt
skynet_ml-1.2.0.7.dist-info/RECORD
