Metadata-Version: 2.1
Name: skynet-ml
Version: 1.2.0.7
Summary: A hand made machine learning library from scratch, by Thiago Macedo
Home-page: https://github.com/macedoti13/skynet_ml
Author: Thiago Macedo
Author-email: thialmacedo@gmail.com
Classifier: Programming Language :: Python :: 3
Classifier: License :: OSI Approved :: MIT License
Classifier: Operating System :: OS Independent
License-File: LICENSE
